cytotable/__init__.py
cytotable/constants.py
cytotable/convert.py
cytotable/exceptions.py
cytotable/presets.py
cytotable/sources.py
cytotable/utils.py
cytotable-1.1.3.dist-info/METADATA
cytotable-1.1.3.dist-info/WHEEL
cytotable-1.1.3.dist-info/licenses/LICENSE
cytotable-1.1.3.dist-info/RECORD
