Metadata-Version: 2.4
Name: CytoTable
Version: 1.1.3
Summary: Transform CellProfiler and DeepProfiler data for processing image-based profiling readouts with Pycytominer and other Cytomining tools.
License: BSD-3-Clause License
License-File: LICENSE
Keywords: python,cellprofiler,single-cell-analysis,way-lab
Author: Cytomining Community
Requires-Python: >=3.10,<3.14
Classifier: License :: Other/Proprietary License
Classifier: Programming Language :: Python :: 3
Classifier: Programming Language :: Python :: 3.10
Classifier: Programming Language :: Python :: 3.11
Classifier: Programming Language :: Python :: 3.12
Classifier: Programming Language :: Python :: 3.13
Requires-Dist: anndata (<0.12.2) ; python_version < "3.11"
Requires-Dist: anndata (>=0.12.2) ; python_version >= "3.11"
Requires-Dist: botocore (>=1.34.133,<2.0.0)
Requires-Dist: cloudpathlib[all,s3] (>=0.18,<0.24)
Requires-Dist: duckdb (>=0.10.1)
Requires-Dist: numpy (<=1.24.4) ; python_version < "3.11"
Requires-Dist: numpy (>=1.26.0) ; python_version >= "3.11"
Requires-Dist: parsl (>=2023.9.25)
Requires-Dist: pyarrow (>=13.0.0)
Requires-Dist: scipy (<1.12.0) ; python_version < "3.9"
Requires-Dist: scipy (>=1.12.0,<2.0.0) ; python_version >= "3.9"
Requires-Dist: zarr (<3.1.1) ; python_version < "3.11"
Requires-Dist: zarr (>=3.1.1) ; python_version >= "3.11"
Project-URL: Documentation, https://cytomining.github.io/CytoTable/
Project-URL: Repository, https://github.com/cytomining/CytoTable
